trainerbase/__init__.py
trainerbase/abc.py
trainerbase/codeinjection.py
trainerbase/common/__init__.py
trainerbase/common/abc.py
trainerbase/common/helpers.py
trainerbase/common/keyboard.py
trainerbase/common/rainbow.py
trainerbase/common/tapper.py
trainerbase/common/teleport.py
trainerbase/config.py
trainerbase/gameobject.py
trainerbase/gui/__init__.py
trainerbase/gui/helpers.py
trainerbase/gui/injections.py
trainerbase/gui/misc.py
trainerbase/gui/objects.py
trainerbase/gui/rainbow.py
trainerbase/gui/scripts.py
trainerbase/gui/speedhack.py
trainerbase/gui/tapper.py
trainerbase/gui/teleport.py
trainerbase/gui/types.py
trainerbase/logger.py
trainerbase/main.py
trainerbase/memory.py
trainerbase/process.py
trainerbase/py.typed
trainerbase/scriptengine.py
trainerbase/speedhack.py
trainerbase/tts.py
trainerbase/vendor/FASM.EXE
trainerbase/vendor/big_logo.png
trainerbase/vendor/speedhack32.dll
trainerbase/vendor/speedhack64.dll
trainerbase/vendor/trainerbase.ico
trainerbase-4.7.0.dist-info/WHEEL
trainerbase-4.7.0.dist-info/METADATA
trainerbase-4.7.0.dist-info/RECORD
