Metadata-Version: 2.4
Name: trainerbase
Version: 4.7.0
Summary: Framework for creating game trainers/mods
Author: v01d, doomayka
Author-email: v01d <v01d@v01d.ru>, doomayka <doomaykaka@gmail.com>
License-Expression: MIT
Classifier: Programming Language :: Python :: Implementation :: CPython
Classifier: Programming Language :: Python :: 3.14
Requires-Dist: dearpygui>=2.1.1
Requires-Dist: keyboard>=0.13.5
Requires-Dist: mouse>=0.7.1
Requires-Dist: psutil>=7.1.3
Requires-Dist: pydantic>=2.12.5
Requires-Dist: pymem>=1.14.0
Requires-Dist: pyttsx3>=2.99
Requires-Dist: trainerbase-injector>=1.0.1
Requires-Python: >=3.14
Project-URL: Homepage, https://gitlab.com/python-trainers/
Project-URL: Repository, https://gitlab.com/python-trainers/trainer-base
